{"id":"037f7219-5de8-4503-b24e-f3da11672cd0","title":"Авокадо с кинзой и лимонным соком","properties":{"lightness":"Light","units":"METRIC","cooking_time":10},"short_description":"Простой и освежающий салат из авокадо, приправленный лимонным соком и зеленью кинзы.","ingredients":["1 спелое авокадо","1 столовая ложка лимонного сока","1 столовая ложка оливкового масла","Несколько веточек свежей кинзы","Соль и черный перец по вкусу"],"steps":[{"index":1,"offset":0,"title":"Подготовка авокадо","description":"Разрежьте авокадо пополам, удалите косточку и аккуратно выньте мякоть ложкой. Нарежьте мякоть авокадо на кубики среднего размера."},{"index":2,"offset":5,"title":"Заправка","description":"В миске смешайте лимонный сок, оливковое масло, мелко нарезанную кинзу. Добавьте соль и перец по вкусу."},{"index":3,"offset":7,"title":"Сборка салата","description":"Добавьте нарезанный авокадо в миску с заправкой, аккуратно перемешайте и позвольте салату пропитаться в течение нескольких минут перед подачей на стол."}],"language":"RU"}