{"id":"2d2fe432-f20b-4ba8-bd75-829193147298","title":"Маринад для свиного стейка","properties":{"lightness":"ANY","units":"METRIC","cooking_time":240},"short_description":"Ароматный маринад, который делает свиной стейк сочным и нежным, пропитывая мясо вкусами специй.","ingredients":["4 столовые ложки соевого соуса","1 столовая ложка меда","2 зубчика чеснока","1 чайная ложка молотого черного перца","1 чайная ложка розмарина","1/2 чайной ложки красного перца чили","50 мл оливкового масла","1 килограмм свиной стейк"],"steps":[{"index":1,"offset":0,"title":"Подготовка ингредиентов","description":"Измельчить чеснок, подготовить соевый соус, мед, перцы, розмарин и оливковое масло."},{"index":2,"offset":10,"title":"Смешивание маринада","description":"Смешать в глубокой миске соевый соус, мед, измельченный чеснок, черный перец, розмарин и молотый чили."},{"index":3,"offset":15,"title":"Добавить масло","description":"Добавить оливковое масло к смеси и перемешать до однородности."},{"index":4,"offset":20,"title":"Маринование стейка","description":"Положить стейки в маринад так, чтобы маринад полностью покрыл мясо. Покрыть и оставить мариноваться на 4 часа в холодильнике."},{"index":5,"offset":240,"title":"Маринованное мясо готово к приготовлению","description":"Вынуть стейки из холодильника; они готовы к жарке или грилю."}],"image_url":null,"language":"RU"}